virtosecure/__init__.py
virtosecure-0.1.dist-info/METADATA
virtosecure-0.1.dist-info/WHEEL
virtosecure-0.1.dist-info/top_level.txt
virtosecure-0.1.dist-info/RECORD
