Metadata-Version: 2.2
Name: virtosecure
Version: 0.1
Summary: An advanced encryption/decryption and VIRTO-1024 hashing package
Author: Zack
Classifier: Programming Language :: Python :: 3
Classifier: License :: OSI Approved :: MIT License
Classifier: Operating System :: OS Independent
Requires-Python: >=3.6
Dynamic: author
Dynamic: classifier
Dynamic: description
Dynamic: description-content-type
Dynamic: requires-python
Dynamic: summary
